tmuxssh.py
tmuxssh-1.1.1.data/scripts/tmuxssh.py
tmuxssh-1.1.1.dist-info/DESCRIPTION.rst
tmuxssh-1.1.1.dist-info/METADATA
tmuxssh-1.1.1.dist-info/RECORD
tmuxssh-1.1.1.dist-info/WHEEL
tmuxssh-1.1.1.dist-info/entry_points.txt
tmuxssh-1.1.1.dist-info/metadata.json
tmuxssh-1.1.1.dist-info/top_level.txt
