Metadata-Version: 2.0
Name: tmuxssh
Version: 1.1.1
Summary: ssh into several hosts at once using tmux
Home-page: http://github.com/spappier/tmuxssh
Author: Santiago Pappier
Author-email: spappier@gmail.com
License: MIT
Keywords: tmux ssh
Platform: UNKNOWN
Classifier: Development Status :: 4 - Beta
Classifier: Intended Audience :: Developers
Classifier: Topic :: Utilities
Classifier: License :: OSI Approved :: MIT License
Classifier: Programming Language :: Python :: 2.7
Classifier: Programming Language :: Python :: 3.5
Requires-Dist: docopt
